bbsky-0.1.6.dist-info/METADATA
bbsky-0.1.6.dist-info/WHEEL
bbsky-0.1.6.dist-info/entry_points.txt
bbsky-0.1.6.dist-info/licenses/LICENSE
bbsky/__init__.py
bbsky/apis.py
bbsky/auth.py
bbsky/cache.py
bbsky/cli.py
bbsky/client.py
bbsky/config.py
bbsky/constants.py
bbsky/crm_constituent_client/__init__.py
bbsky/crm_constituent_client/api/__init__.py
bbsky/crm_constituent_client/api/alternate_lookup_id/__init__.py
bbsky/crm_constituent_client/api/alternate_lookup_id/create_constituent_alternate_lookup_id.py
bbsky/crm_constituent_client/api/alternate_lookup_id/delete_constituent_alternate_lookup_id.py
bbsky/crm_constituent_client/api/alternate_lookup_id/edit_constituent_alternate_lookup_id.py
bbsky/crm_constituent_client/api/alternate_lookup_id/get_constituent_alternate_lookup_id.py
bbsky/crm_constituent_client/api/alternate_lookup_id/list_constituent_alternate_lookup_ids.py
bbsky/crm_constituent_client/api/constituent/__init__.py
bbsky/crm_constituent_client/api/constituent/create_constituent.py
bbsky/crm_constituent_client/api/constituent/delete_constituent.py
bbsky/crm_constituent_client/api/constituent/search_constituents.py
bbsky/crm_constituent_client/api/constituent/view_constituent_profile_picture.py
bbsky/crm_constituent_client/api/constituent/view_constituent_summary_profile.py
bbsky/crm_constituent_client/api/constituent_address/__init__.py
bbsky/crm_constituent_client/api/constituent_address/create_constituent_address.py
bbsky/crm_constituent_client/api/constituent_address/delete_constituent_address.py
bbsky/crm_constituent_client/api/constituent_address/edit_constituent_address.py
bbsky/crm_constituent_client/api/constituent_address/get_constituent_address.py
bbsky/crm_constituent_client/api/constituent_address/list_constituent_addresses.py
bbsky/crm_constituent_client/api/constituent_address/search_constituent_addresses.py
bbsky/crm_constituent_client/api/constituent_address/view_constituent_address.py
bbsky/crm_constituent_client/api/constituent_appeal/__init__.py
bbsky/crm_constituent_client/api/constituent_appeal/create_constituent_appeal.py
bbsky-0.1.6.dist-info/RECORD
