Metadata-Version: 2.1
Name: bbsky
Version: 0.1.6
Summary: Client for Blackbaud Sky API
Author-Email: dcbark01 <dcbark01@gmail.com>
Requires-Python: >=3.10
Requires-Dist: attrs>=24.2.0
Requires-Dist: cattrs>=24.1.2
Requires-Dist: bottle>=0.13.1
Requires-Dist: yarl>=1.14.0
Requires-Dist: httpx>=0.27.2
Requires-Dist: pendulum>=3.0.0
Requires-Dist: python-dateutil>=2.9.0.post0
Requires-Dist: typer>=0.12.5
Requires-Dist: hishel>=0.1.1
Requires-Dist: blake3>=0.4.1
Requires-Dist: tenacity>=9.0.0
Requires-Dist: rich>=13.9.4
